aiotba/__init__.py
aiotba/consts.py
aiotba/http.py
aiotba/models.py
aiotba-0.0.2.post1.dist-info/LICENSE
aiotba-0.0.2.post1.dist-info/METADATA
aiotba-0.0.2.post1.dist-info/WHEEL
aiotba-0.0.2.post1.dist-info/top_level.txt
aiotba-0.0.2.post1.dist-info/RECORD
