Metadata-Version: 2.1
Name: aiotba
Version: 0.0.2.post1
Summary: a lib for the blue alliance (TBA) apiv3 using asyncio/aiohttp
Home-page: https://github.com/guineawheek/aiotba
Author: guineawheek
Author-email: guineawheek@gmail.com
License: MIT
Platform: UNKNOWN
Classifier: Programming Language :: Python :: 3
Classifier: License :: OSI Approved :: MIT License
Classifier: Operating System :: OS Independent
Requires-Dist: aiohttp
